scrapy_logexport/__init__.py
scrapy_logexport/extension.py
scrapy_logexport-0.2.1.dist-info/LICENSE
scrapy_logexport-0.2.1.dist-info/METADATA
scrapy_logexport-0.2.1.dist-info/WHEEL
scrapy_logexport-0.2.1.dist-info/RECORD
