Metadata-Version: 2.1
Name: scrapy-logexport
Version: 0.2.1
Summary: Upload scrapy logs to cloud storage
Home-page: https://github.com/nicholas-mischke/scrapy-logexport
License: MIT
Author: Nicholas Mischke
Author-email: nmischkework@proton.me
Requires-Python: >=3.7,<4.0
Classifier: License :: OSI Approved :: MIT License
Classifier: Programming Language :: Python :: 3
Classifier: Programming Language :: Python :: 3.7
Classifier: Programming Language :: Python :: 3.8
Classifier: Programming Language :: Python :: 3.9
Classifier: Programming Language :: Python :: 3.10
Classifier: Programming Language :: Python :: 3.11
Requires-Dist: botocore (>=1.29.143,<2.0.0)
Project-URL: Repository, https://github.com/nicholas-mischke/scrapy-logexport
